[{"id":"3c8143ca.cbb4ec","type":"tab","label":"Flow 1","disabled":false,"info":""},{"id":"161f5a01.3f4546","type":"ui_base","theme":{"name":"theme-light","lightTheme":{"default":"#0094CE","baseColor":"#0094CE","baseFont":"-apple-system,BlinkMacSystemFont,Segoe UI,Roboto,Oxygen-Sans,Ubuntu,Cantarell,Helvetica Neue,sans-serif","edited":true,"reset":false},"darkTheme":{"default":"#097479","baseColor":"#097479","baseFont":"-apple-system,BlinkMacSystemFont,Segoe UI,Roboto,Oxygen-Sans,Ubuntu,Cantarell,Helvetica Neue,sans-serif","edited":false},"customTheme":{"name":"Untitled Theme 1","default":"#4B7930","baseColor":"#4B7930","baseFont":"-apple-system,BlinkMacSystemFont,Segoe UI,Roboto,Oxygen-Sans,Ubuntu,Cantarell,Helvetica Neue,sans-serif"},"themeState":{"base-color":{"default":"#0094CE","value":"#0094CE","edited":false},"page-titlebar-backgroundColor":{"value":"#0094CE","edited":false},"page-backgroundColor":{"value":"#fafafa","edited":false},"page-sidebar-backgroundColor":{"value":"#ffffff","edited":false},"group-textColor":{"value":"#1bbfff","edited":false},"group-borderColor":{"value":"#ffffff","edited":false},"group-backgroundColor":{"value":"#ffffff","edited":false},"widget-textColor":{"value":"#111111","edited":false},"widget-backgroundColor":{"value":"#0094ce","edited":false},"widget-borderColor":{"value":"#ffffff","edited":false},"base-font":{"value":"-apple-system,BlinkMacSystemFont,Segoe UI,Roboto,Oxygen-Sans,Ubuntu,Cantarell,Helvetica Neue,sans-serif"}}},"site":{"name":"Node-RED Dashboard","hideToolbar":"false","allowSwipe":"false","allowTempTheme":"true","dateFormat":"DD/MM/YYYY","sizes":{"sx":48,"sy":48,"gx":6,"gy":6,"cx":6,"cy":6,"px":0,"py":0}}},{"id":"affcabf9.5a2868","type":"mongodb","z":"","hostname":"oc-nr-meta-mongodb1.oc-node-red-meta-project-1.svc","port":"27017","db":"oc-nr-meta-mongo-db-1","name":"oc-nr-meta-mongo"},{"id":"69f54122.5e5a2","type":"ui_tab","z":"","name":"Home","icon":"dashboard"},{"id":"7f11badc.67bac4","type":"ui_group","z":"","name":"UIGrupoUno","tab":"69f54122.5e5a2","disp":true,"width":"6","collapse":false},{"id":"5e46550a.d54b0c","type":"http in","z":"3c8143ca.cbb4ec","name":"","url":"/meta/csv","method":"post","upload":false,"swaggerDoc":"","x":204,"y":878,"wires":[["40aac99.5630538"]]},{"id":"40aac99.5630538","type":"csv","z":"3c8143ca.cbb4ec","name":"","sep":",","hdrin":true,"hdrout":"","multi":"mult","ret":"\\r\\n","temp":"","skip":"0","x":446,"y":882,"wires":[["1da3902c.6e172"]]},{"id":"bfc787b1.a40168","type":"http response","z":"3c8143ca.cbb4ec","name":"","statusCode":"200","headers":{},"x":684,"y":1011,"wires":[]},{"id":"352447fe.ff43f8","type":"contrib-json","z":"3c8143ca.cbb4ec","engine":"JSONSelect","command":"jq","expr":".PRODUCTO","complete":"property","prop":"payload","name":"","x":768,"y":702,"wires":[["dc7380e4.7eedd"]]},{"id":"dc7380e4.7eedd","type":"debug","z":"3c8143ca.cbb4ec","name":"","active":true,"tosidebar":true,"console":false,"tostatus":false,"complete":"false","x":1117,"y":811,"wires":[]},{"id":"23dc4607.ad034a","type":"http response","z":"3c8143ca.cbb4ec","name":"","statusCode":"200","headers":{},"x":952.1000137329102,"y":629.8000583648682,"wires":[]},{"id":"1da3902c.6e172","type":"marko-ui","z":"3c8143ca.cbb4ec","name":"","projectName":"node-red-project-meta-expander","path":"/opt/app-root/src/.node-red/projects/node-red-project-meta-expander","templatesFolder":"components","template":"test1","field":"payload","x":686.1000061035156,"y":604.6000061035156,"wires":[["23dc4607.ad034a"]]}]